<?xml version="1.0" encoding="UTF-8" standalone="yes"?>
<resultatValidacio>
    <informacioCertificat>
        <altresValors/>
        <certificatQualificat>true</certificatQualificat>
        <classificacio>0</classificacio>
        <classificacioEidas>ESIG</classificacioEidas>
        <creatAmbUnDispositiuSegur>false</creatAmbUnDispositiuSegur>
        <emissorID>CN=EC-Ciutadania,OU=Serveis Públics de Certificació,O=CONSORCI ADMINISTRACIO OBERTA DE CATALUNYA,C=ES</emissorID>
        <emissorOrganitzacio>CONSORCI ADMINISTRACIO OBERTA DE CATALUNYA</emissorOrganitzacio>
        <idEuropeu>IDCES-00000000T</idEuropeu>
        <llinatgesResponsable>de la Peça de Prova</llinatgesResponsable>
        <nifResponsable>00000000T</nifResponsable>
        <nomCompletResponsable>Persona de la Peça de Prova</nomCompletResponsable>
        <nomResponsable>Persona</nomResponsable>
        <numeroSerie>8445329700304316470</numeroSerie>
        <pais>ES</pais>
        <politica>1.3.6.1.4.1.15096.1.3.2.86.2,0.4.0.194112.1.0</politica>
        <politicaID>MITyC</politicaID>
        <politicaVersio>23</politicaVersio>
        <subject>CN=Persona de la Peça de Prova - DNI 00000000T,serialNumber=IDCES-00000000T,givenName=Persona,SN=de la Peça de Prova,C=ES</subject>
        <tipusCertificat>CATCERT CIUTADANIA PF CPISA-2</tipusCertificat>
        <usCertificat>digitalSignature | nonRepudiation | keyEncipherment</usCertificat>
        <usCertificatExtensio>KeyPurposeId 0:  TLS Web client authentication
KeyPurposeId 1:  E-mail protection</usCertificatExtensio>
        <validDesDe>2018-05-15T09:50:00+02:00</validDesDe>
        <validFins>2018-05-15T11:39:31+02:00</validFins>
    </informacioCertificat>
    <resultatValidacioCodi>1</resultatValidacioCodi>
    <resultatValidacioDescripcio>El certificado no paso la validacion</resultatValidacioDescripcio>
</resultatValidacio>
